DeepMuon/__init__.py
DeepMuon/__version__.py
DeepMuon/dataset/CMRData.py
DeepMuon/dataset/EGFRData.py
DeepMuon/dataset/HailingData.py
DeepMuon/dataset/Pandax4TData.py
DeepMuon/dataset/XASData.py
DeepMuon/dataset/__init__.py
DeepMuon/interpret/__init__.py
DeepMuon/interpret/attribution.py
DeepMuon/interpret/profiler.py
DeepMuon/interpret/tracer.py
DeepMuon/loss_fn/FocalLoss.py
DeepMuon/loss_fn/MSALoss.py
DeepMuon/loss_fn/__init__.py
DeepMuon/loss_fn/evaluation.py
DeepMuon/models/CNNLSTM.py
DeepMuon/models/MLPMixer.py
DeepMuon/models/Pandax4T.py
DeepMuon/models/ResMax2.py
DeepMuon/models/SwinTrans.py
DeepMuon/models/Unet.py
DeepMuon/models/VST.py
DeepMuon/models/ViT.py
DeepMuon/models/__init__.py
DeepMuon/models/cryoFIRE.py
DeepMuon/tools/AirConfig.py
DeepMuon/tools/AirFunc.py
DeepMuon/tools/AirLogger.py
DeepMuon/tools/__init__.py
DeepMuon/tools/mem_info.py
DeepMuon/tools/model_info.py
DeepMuon/train/__init__.py
DeepMuon/train/dist_train.py
DeepMuon/train/pipeline.py
DeepMuon/train/run.py
DeepMuon-1.23.51.dist-info/LICENSE.txt
DeepMuon-1.23.51.dist-info/METADATA
DeepMuon-1.23.51.dist-info/WHEEL
DeepMuon-1.23.51.dist-info/entry_points.txt
DeepMuon-1.23.51.dist-info/top_level.txt
DeepMuon-1.23.51.dist-info/RECORD
