Metadata-Version: 2.1
Name: DeepMuon
Version: 1.23.51
Summary: Interdisciplinary Deep Learning Platform
Home-page: https://airscker.github.io/DeepMuon/
Author: Airscker/Yufeng Wang
Author-email: airscker@gmail.com
License: UNKNOWN
Keywords: Deep Learning,Searching Dark Matter,Direct and Simple
Platform: UNKNOWN
Classifier: Development Status :: 3 - Alpha
Classifier: Intended Audience :: Developers
Classifier: Topic :: Software Development :: Build Tools
Classifier: License :: OSI Approved :: GNU Lesser General Public License v3 (LGPLv3)
Classifier: Programming Language :: Python :: 3
Classifier: Programming Language :: Python :: 3.7
Classifier: Programming Language :: Python :: 3.8
Classifier: Programming Language :: Python :: 3.9
Classifier: Programming Language :: Python :: 3.10
Classifier: Programming Language :: Python :: 3 :: Only
Requires-Python: >=3.6, <4
License-File: LICENSE.txt
Requires-Dist: click
Requires-Dist: tqdm
Requires-Dist: numpy
Requires-Dist: pandas
Requires-Dist: numba
Requires-Dist: ptflops
Requires-Dist: torchinfo
Requires-Dist: captum
Requires-Dist: monai
Requires-Dist: pynvml
Requires-Dist: psutil
Requires-Dist: GPUtil
Requires-Dist: matplotlib
Requires-Dist: timm
Requires-Dist: SimpleITK
Requires-Dist: scikit-learn
Requires-Dist: scikit-image
Requires-Dist: tensorboard
Requires-Dist: yapf
Requires-Dist: parso
